pygments_ayed2/__init__.py
pygments_ayed2/lexer.py
pygments_ayed2/style.py
pygments_ayed2-0.1.2.dist-info/LICENSE
pygments_ayed2-0.1.2.dist-info/METADATA
pygments_ayed2-0.1.2.dist-info/WHEEL
pygments_ayed2-0.1.2.dist-info/entry_points.txt
pygments_ayed2-0.1.2.dist-info/RECORD
